rest2/__init__.py
rest2/rest2.py
rest2/version.py
NREL_rest2-1.0.2.dist-info/LICENSE
NREL_rest2-1.0.2.dist-info/METADATA
NREL_rest2-1.0.2.dist-info/WHEEL
NREL_rest2-1.0.2.dist-info/top_level.txt
NREL_rest2-1.0.2.dist-info/RECORD
