Metadata-Version: 2.1
Name: NREL-rest2
Version: 1.0.2
Summary: REST2 is the High-performance solar radiation model for cloudless-sky irradiance, illuminance, and photosynthetically active radiation
Home-page: https://github.com/NREL/
Author: Grant Buster
Author-email: grant.buster@nrel.gov
Keywords: rest2
Classifier: Development Status :: 4 - Beta
Classifier: Intended Audience :: Science/Research
Classifier: License :: OSI Approved :: BSD License
Classifier: Natural Language :: English
Classifier: Programming Language :: Python :: 3.6
Classifier: Programming Language :: Python :: 3.7
Classifier: Programming Language :: Python :: 3.8
Classifier: Programming Language :: Python :: 3.9
Requires-Python: >=3.6
License-File: LICENSE
Requires-Dist: NREL-farms >=1.0.0
Requires-Dist: numpy >=1.17
Requires-Dist: h5py !=3.0.0,>=2.10.0
Provides-Extra: dev
Requires-Dist: pytest >=5.2 ; extra == 'dev'
Requires-Dist: flake8 ; extra == 'dev'
Requires-Dist: pre-commit ; extra == 'dev'
Requires-Dist: pylint ; extra == 'dev'
Provides-Extra: test
Requires-Dist: pytest >=5.2 ; extra == 'test'
